ec_driver/__init__.py
ec_driver/py.typed
ec_driver-0.1.0.dist-info/WHEEL
ec_driver-0.1.0.dist-info/METADATA
ec_driver-0.1.0.dist-info/RECORD
