Metadata-Version: 2.3
Name: ec-driver
Version: 0.1.0
Summary: eChecker driver library for Python
Author: Maximilian Köhl
Author-email: Maximilian Köhl <koehl@silitics.com>
Requires-Python: >=3.14
